Workbook

Sheet Financials
A1: Income Statement As of Originally Reported | B1: 2015 | C1: 2016 | D1: 2017 | E1: 2018 | F1: 2019 | G1: 2020 | H1: 2021 | I1: 2022 | J1: 2023 | K1: 2024
A2: Revenue | B2: 97310000000 | C2: 81410000000 | D2: 88830000000 | E2: 95580000000 | F2: 76590000000 | G2: 53680000000 | H2: 83970000000 | I2: 124470000000 | J2: 102410000000 | K2: 91420000000
A3: Revenue Growth % | B3: -32.26 | C3: -16.35 | D3: 9.12 | E3: 22.73 | F3: -9.51 | G3: -29.91 | H3: 56.41 | I3: 48.24 | J3: -17.73 | K3: -10.73
A4: Gross Profit | B4: 29830000000 | C4: 25990000000 | D4: 28680000000 | E4: 34070000000 | F4: 30860000000 | G4: 24490000000 | H4: 40800000000 | I4: 64990000000 | J4: 53970000000 | K4: 45970000000
A5: Gross Profit Margin % | B5: 30.65 | C5: 31.92 | D5: 32.29 | E5: 35.64 | F5: 40.29 | G5: 45.62 | H5: 48.59 | I5: 52.21 | J5: 52.70 | K5: 50.29
A6: Operating Income | B6: 14710000000 | C6: 14440000000 | D6: 13020000000 | E6: 23220000000 | F6: 17180000000 | G6: 16510000000 | H6: 33330000000 | I6: 55630000000 | J6: 39490000000 | K6: 25690000000
A7: Operating Margin % | B7: 15.11 | C7: 17.73 | D7: 14.66 | E7: 24.29 | F7: 22.43 | G7: 30.76 | H7: 39.69 | I7: 44.69 | J7: 38.56 | K7: 28.10
A8: EBIT | B8: -5380000000 | C8: 1820000000 | D8: 6810000000 | E8: 15740000000 | F8: 18680000000 | G8: 5470000000 | H8: 33200000000 | I8: 56160000000 | J8: 39020000000 | K8: 14980000000
A9: EBIT Margin % | B9: -5.53 | C9: 2.23 | D9: 7.66 | E9: 16.47 | F9: 24.39 | G9: 10.18 | H9: 39.54 | I9: 45.12 | J9: 38.10 | K9: 16.39
A10: EBITDA | B10: 6210000000 | C10: 15780000000 | D10: 20110000000 | E10: 27770000000 | F10: 33520000000 | G10: 17860000000 | H10: 46220000000 | I10: 70860000000 | J10: 52300000000 | K10: 27460000000
A11: EBITDA Margin % | B11: 6.38 | C11: 19.39 | D11: 22.64 | E11: 29.05 | F11: 43.76 | G11: 33.27 | H11: 55.04 | I11: 56.93 | J11: 51.07 | K11: 30.04
A12: Net Income | B12: -8450000000 | C12: -4840000000 | D12: -90000000 | E12: 7170000000 | F12: 10150000000 | G12: 1140000000 | H12: 19880000000 | I12: 36620000000 | J12: 24880000000 | K12: 7530000000
A13: Net Profit Margin % | B13: -8.85 | C13: -5.34 | D13: 0.19 | E13: 7.76 | F13: 10.19 | G13: 1.77 | H13: 23.80 | I13: 29.53 | J13: 24.41 | K13: 8.32
A14: Basic EPS | B14: -1.30 | C14: -0.74 | D14: -0.02 | E14: 1.10 | F14: 1.56 | G14: 0.18 | H14: 3.04 | I14: 5.62 | J14: 3.82 | K14: 1.16
A15: Diluted EPS | B15: -1.30 | C15: -0.74 | D15: -0.02 | E15: 1.10 | F15: 1.56 | G15: 0.18 | H15: 3.04 | I15: 5.62 | J15: 3.82 | K15: 1.16
A16: Normalized EPS | B16: - | C16: - | D16: - | E16: 1.25 | F16: 1.93 | G16: 1.35 | H16: 2.25 | I16: 5.16 | J16: 4.21 | K16: 1.89
A17: Dividend Per Share | B17: - | C17: - | D17: - | E17: 0.11 | F17: 0.27 | G17: 0.09 | H17: 2.04 | I17: 6.45 | J17: 2.98 | K17: 2.35
A18: Balance Sheet As of Originally Reported | B18: 2015 | C18: 2016 | D18: 2017 | E18: 2018 | F18: 2019 | G18: 2020 | H18: 2021 | I18: 2022 | J18: 2023 | K18: 2024
A19: Total Assets | B19: 230520000000 | C19: 246980000000 | D19: 251370000000 | E19: 222070000000 | F19: 229740000000 | G19: 190010000000 | H19: 174350000000 | I19: 187190000000 | J19: 217070000000 | K19: 181650000000
A20: Total Liabilities | B20: 164470000000 | C20: 169430000000 | D20: 169860000000 | E20: 148890000000 | F20: 155530000000 | G20: 130130000000 | H20: 104540000000 | I20: 117360000000 | J20: 138090000000 | K20: 122300000000
A21: Total Debt | B21: 126220000000 | C21: 118370000000 | D21: 109280000000 | E21: 84360000000 | F21: 87120000000 | G21: 75540000000 | H21: 58740000000 | I21: 53800000000 | J21: 62600000000 | K21: 60310000000
A22: Total Equity | B22: 66060000000 | C22: 77550000000 | D22: 81500000000 | E22: 73180000000 | F22: 74220000000 | G22: 59880000000 | H22: 69810000000 | I22: 69840000000 | J22: 78980000000 | K22: 59350000000
A23: Cash And Cash Equivalents | B23: 25060000000 | C23: 21210000000 | D23: 22520000000 | E23: 13900000000 | F23: 7370000000 | G23: 11710000000 | H23: 10470000000 | I23: 8000000000 | J23: 12730000000 | K23: 3270000000
A24: Working Capital | B24: 14860000000 | C24: 19870000000 | D24: 22180000000 | E24: 12010000000 | F24: -1000000000 | G24: 1160000000 | H24: 5970000000 | I24: -130000000 | J24: -1420000000 | K24: -9620000000
A25: Shares Outstanding Capital | B25: 6522248465 | C25: 6522248465 | D25: 6522248465 | E25: 6522100631 | F25: 6522100631 | G25: 6522100631 | H25: 6522100631 | I25: 6522100631 | J25: 6470068631 | K25: 6454643831
A26: Book Value per Share | B26: 10.00 | C26: 11.77 | D26: 12.24 | E26: 10.97 | F26: 11.24 | G26: 9.10 | H26: 10.64 | I26: 10.65 | J26: 12.15 | K26: 9.17
A27: Debt to Equity | B27: 1.91 | C27: 1.53 | D27: 1.34 | E27: 1.15 | F27: 1.17 | G27: 1.26 | H27: 0.84 | I27: 0.77 | J27: 0.79 | K27: 1.02
A28: Cash Flow As of Originally Reported | B28: 2015 | C28: 2016 | D28: 2017 | E28: 2018 | F28: 2019 | G28: 2020 | H28: 2021 | I28: 2022 | J28: 2023 | K28: 2024
A29: Cash From Operating Activities | B29: 25910000000 | C29: 26110000000 | D29: 27110000000 | E29: 26350000000 | F29: 25600000000 | G29: 28890000000 | H29: 37790000000 | I29: 49720000000 | J29: 43210000000 | K29: 37980000000
A30: Cash From Investing Activities | B30: -12790000000 | C30: -11300000000 | D30: -11030000000 | E30: -4760000000 | F30: -1680000000 | G30: -4510000000 | H30: 2160000000 | I30: -430000000 | J30: -7960000000 | K30: -13370000000
A31: Cash From Financing Activities | B31: -3590000000 | C31: -19110000000 | D31: -14640000000 | E31: -29590000000 | F31: -32070000000 | G31: -19260000000 | H31: -40790000000 | I31: -51450000000 | J31: -30700000000 | K31: -33090000000
A32: Capital Expenditure | B32: 21650000000 | C32: 14090000000 | D32: 13640000000 | E32: 12020000000 | F32: 23900000000 | G32: 5870000000 | H32: 6330000000 | I32: 9580000000 | J32: 12110000000 | K32: 14640000000
A33: Free Cash Flow | B33: 160000000 | C33: 6700000000 | D33: 8640000000 | E33: 10970000000 | F33: 3300000000 | G33: 17430000000 | H33: 29800000000 | I33: 44830000000 | J33: 32890000000 | K33: 25100000000
A34: Change in Cash | B34: 9530000000 | C34: -4300000000 | D34: 1440000000 | E34: -8000000000 | F34: -8150000000 | G34: 5120000000 | H34: -840000000 | I34: -2170000000 | J34: 4560000000 | K34: -8470000000

Sheet Financial ratios
B1: 2015 | C1: 2016 | D1: 2017 | E1: 2018 | F1: 2019 | G1: 2020 | H1: 2021 | I1: 2022 | J1: 2023 | K1: 2024 | M1: Mean | N1: Median | O1: Industry (Median)
A2: Profitability ratio
A3: Gross Profit Margin % | B3: 30.65 | C3: 31.92 | D3: 32.29 | E3: 35.64 | F3: 40.29 | G3: 45.62 | H3: 48.59 | I3: 52.21 | J3: 52.7 | K3: 50.29 | M3: =AVERAGE(B3:K3) -> 42.02 | N3: =MEDIAN(B3:K3) -> 42.955 | O3: 42.3
A4: Operating Margin % | B4: 15.11 | C4: 17.73 | D4: 14.66 | E4: 24.29 | F4: 22.43 | G4: 30.76 | H4: 39.69 | I4: 44.69 | J4: 38.56 | K4: 28.1 | M4: =AVERAGE(B4:K4) -> 27.602 | N4: =MEDIAN(B4:K4) -> 26.195 | O4: 4.65
A5: Net Profit Margin % | B5: -8.85 | C5: -5.34 | D5: 0.19 | E5: 7.76 | F5: 10.19 | G5: 1.77 | H5: 23.8 | I5: 29.53 | J5: 24.41 | K5: 8.32 | M5: =AVERAGE(B5:K5) -> 9.178 | N5: =MEDIAN(B5:K5) -> 8.04 | O5: 1.75
A7: Liquidity ratio
A8: Current Ratio | B8: 1.52 | C8: 1.8 | D8: 1.89 | E8: 1.48 | F8: 0.97 | G8: 1.04 | H8: 1.25 | I8: 1 | J8: 0.96 | K8: 0.69 | M8: =AVERAGE(B8:K8) -> 1.26 | N8: =MEDIAN(B8:K8) -> 1.145 | O8: 1.2285
A9: Quick Ratio | B9: 1.2 | C9: 1.18 | D9: 1.28 | E9: 0.91 | F9: 0.54 | G9: 0.75 | H9: 0.78 | I9: 0.54 | J9: 0.68 | K9: 0.42 | M9: =AVERAGE(B9:K9) -> 0.828 | N9: =MEDIAN(B9:K9) -> 0.765 | O9: 1.0515
A11: Working Capital Ratios
A12: Cash Conversion Cycle | B12: 33.31 | C12: 36.13 | D12: 36.5 | E12: 36.43 | F12: 43.6 | G12: 37.66 | H12: 26.62 | I12: 32.29 | J12: 43.16 | K12: 33.41 | M12: =AVERAGE(B12:K12) -> 35.911 | N12: =MEDIAN(B12:K12) -> 36.28 | O12: 37.867
A13: Inventory Turnover | B13: 7.14 | C13: 6.96 | D13: 7.09 | E13: 7.04 | F13: 5.33 | G13: 4.21 | H13: 6.68 | I13: 7.42 | J13: 5.89 | K13: 6.32 | M13: =AVERAGE(B13:K13) -> 6.408 | N13: =MEDIAN(B13:K13) -> 6.82 | O13: 17.727
A14: Asset Turnover | B14: 0.37 | C14: 0.34 | D14: 0.36 | E14: 0.4 | F14: 0.34 | G14: 0.26 | H14: 0.46 | I14: 0.69 | J14: 0.51 | K14: 0.46 | M14: =AVERAGE(B14:K14) -> 0.419 | N14: =MEDIAN(B14:K14) -> 0.385 | O14: 0.355
A16: Leverage Ratios
A17: Interest Coverage | B17: -0.92 | C17: 0.39 | D17: 1.37 | E17: 3.88 | F17: 2.8 | G17: 0.96 | H17: 6.67 | I17: 17.17 | J17: 10.78 | K17: 3.9 | M17: =AVERAGE(B17:K17) -> 4.7 | N17: =MEDIAN(B17:K17) -> 3.34 | O17: 1.643
A18: Debt/Equity | B18: 1.71 | C18: 1.41 | D18: 1.28 | E18: 1.13 | F18: 1.05 | G18: 1.11 | H18: 0.72 | I18: 0.64 | J18: 0.65 | K18: 0.83 | M18: =AVERAGE(B18:K18) -> 1.053 | N18: =MEDIAN(B18:K18) -> 1.08 | O18: 0.9515
A19: Debt/Capital | B19: =ROUND(Financials!B21 /(Financials!B21+ Financials!B22), 2) -> 0.66 | C19: =ROUND(Financials!C21 /(Financials!C21+ Financials!C22), 2) -> 0.6 | D19: =ROUND(Financials!D21 /(Financials!D21+ Financials!D22), 2) -> 0.57 | E19: =ROUND(Financials!E21 /(Financials!E21+ Financials!E22), 2) -> 0.54 | F19: =ROUND(Financials!F21 /(Financials!F21+ Financials!F22), 2) -> 0.54 | G19: =ROUND(Financials!G21 /(Financials!G21+ Financials!G22), 2) -> 0.56 | H19: =ROUND(Financials!H21 /(Financials!H21+ Financials!H22), 2) -> 0.46 | I19: =ROUND(Financials!I21 /(Financials!I21+ Financials!I22), 2) -> 0.44 | ... K19: =ROUND(Financials!K21 /(Financials!K21+ Financials!K22), 2) -> 0.5 | M19: =AVERAGE(B19:K19) -> 0.531 | N19: =MEDIAN(B19:K19) -> 0.54 | O19: 0.4415
A21: Valuation Ratios
A22: P/B Ratio | B22: — | C22: 0.82 | D22: 0.81 | E22: 1.17 | F22: 1.41 | G22: 1.67 | H22: 1.06 | I22: 1.01 | J22: 1.35 | K22: 1.15 | M22: =ROUND(AVERAGE(B22:K22), 2) -> 1.16 | N22: =MEDIAN(B22:K22) -> 1.15 | O22: 1.356
A23: P/E Ratio | B23: — | C23: — | D23: 28.58 | E23: 17.12 | F23: 16.6 | G23: — | H23: 2.79 | I23: 2.04 | J23: 3.88 | K23: 5.02 | M23: =ROUND(AVERAGE(B23:K23), 2) -> 10.86 | N23: =MEDIAN(B23:K23) -> 5.02 | O23: 3.5735
A24: Enterprise Value/EBITDA | B24: — | C24: — | D24: 13.53 | E24: 13.99 | F24: 10.04 | G24: — | H24: 2.93 | I24: 2.12 | J24: 3.68 | K24: 4.64 | M24: =ROUND(AVERAGE(B24:K24), 2) -> 7.28 | N24: =MEDIAN(B24:K24) -> 4.64 | O24: 5.526
A26: Operating Returns
A27: Return on Asset (%) | B27: -0.0319 | C27: -0.0203 | D27: -0.0004 | E27: 0.0303 | F27: 0.0449 | G27: 0.0054 | H27: 0.1091 | I27: 0.2026 | J27: 0.1231 | K27: 0.0378 | M27: =AVERAGE(B27:K27) -> 0.05006 | N27: =MEDIAN(B27:K27) -> 0.03405 | O27: 11.7
A28: Return on Equity (%) | B28: -0.0931 | C28: -0.0681 | D28: -0.0012 | E28: 0.0948 | F28: 0.1401 | G28: 0.0172 | H28: 0.3087 | I28: 0.5273 | J28: 0.3361 | K28: 0.1093 | M28: =AVERAGE(B28:K28) -> 0.13711 | N28: =MEDIAN(B28:K28) -> 0.10205 | O28: 2.7
A29: Return on Invested Capital (%) | B29: -0.0209 | C29: -0.002 | D29: 0.016 | E29: 0.0545 | F29: 0.0916 | G29: 0.0332 | H29: 0.178 | I29: 0.3057 | J29: 0.2075 | K29: 0.0779 | M29: =AVERAGE(B29:K29) -> 0.09415 | N29: =MEDIAN(B29:K29) -> 0.0662 | O29: 3.7

Sheet DDM
A1: Dividend Discount Model
B2: 2020 | C2: 2021 | D2: 2022 | E2: 2023 | F2: 2024 | H2: 5Y Mean | I2: 5Y Median
A3: Dividend per Share | B3: 0.09 | C3: 2.04 | D3: 6.45 | E3: 2.98 | F3: 2.35 | H3: =AVERAGE(B3:F3) -> 2.782 | I3: =MEDIAN(B3:F3) -> 2.35
A4: Dividend Growth Rate | B4: -0.59 | C4: =((C3-B3)/B3) -> 21.666667 | D4: =((D3-C3)/C3) -> 2.1617647 | E4: =((E3-D3)/D3) -> -0.5379845 | F4: =((F3-E3)/E3) -> -0.2114094 | H4: =AVERAGE(B4:F4) -> 4.4978075 | I4: =MEDIAN(B4:F4) -> -0.2114094
A5: Dividend Payout Rate (%) | B5: 52.1 | C5: 67.15 | D5: 114.79 | E5: 78 | F5: 202.33 | H5: =AVERAGE(B5:F5) -> 102.874 | I5: =MEDIAN(B5:F5) -> 78
A6: Trailing Dividend Yield (%) | B6: 0.84 | C6: 18.59 | D6: 60.57 | E6: 18.66 | F6: 21.96 | H6: =AVERAGE(B6:F6) -> 24.124 | I6: =MEDIAN(B6:F6) -> 18.66
A8: Historical growth rate | B8: =I4 -> -0.2114094
A9: Sustainable growth rate | B9: =(1-H5/100)* AVERAGE('Financial ratios'!G28:K28)/100 -> -7.4643528e-05
A10: Implied growth rate | B10: =B11-H6/100 -> -0.06724
A11: Cost of Equity (rE) | B11: 0.174
A13: Scenario I | B13: 5-year at average historical growth, long-run growth at sustainable rate
A14: t | B14: 0 | C14: 1 | D14: 2 | E14: 3 | F14: 4 | G14: 5 | H14: 6
A15: Dividend (End 2024) | B15: =F3 -> 2.35 | C15: =B15*(1+$B$8) -> 1.8531879 | D15: =C15*(1+$B$8) -> 1.4614066 | E15: =D15*(1+$B$8) -> 1.1524515 | F15: =E15*(1+$B$8) -> 0.90881242 | G15: =F15*(1+$B$8) -> 0.71668094 | H15: =G15*(1+B9) -> 0.71662744
A16: PV GP5 | B16: =H15/(B11-B9) -> 4.1167825
A17: PV Div 1-5 | B17: {=NPV(B11,C15:G15)} -> 4.1508334
A18: Estimated Price | B18: =B17+B16/(1+B11)^5 -> 5.9967728
A19: Market Price (1/2/25) | B19: 13.16
A21: Scenario II | B21: 5-year at average historical growth, long-run growth at implied growth rate
A22: t | B22: 0 | C22: 1 | D22: 2 | E22: 3 | F22: 4 | G22: 5 | H22: 6
A23: Dividend (Current) | B23: 2.35 | C23: =B23*(1+$B$8) -> 1.8531879 | D23: =C23*(1+$B$8) -> 1.4614066 | E23: =D23*(1+$B$8) -> 1.1524515 | F23: =E23*(1+$B$8) -> 0.90881242 | G23: =F23*(1+$B$8) -> 0.71668094 | H23: =G23*(1+B10) -> 0.66849131
A24: PV GP5 | B24: =H23/(B11-B10) -> 2.7710633
A25: PV Div 1-5 | B25: {=NPV(B11,C23:G23)} -> 4.1508334
A26: Estimated Price | B26: =B25+B24/(1+B11)^5 -> 5.3933608
A27: Market Price (1/2/25) | B27: 13.16

Sheet DFCF
A1: Discounted Free Cash Flow
B2: 2020 | C2: 2021 | D2: 2022 | E2: 2023 | F2: 2024 | H2: Mean | I2: Median
A3: EBIT/Sales | B3: =Financials!G8/Financials!G2 -> 0.10190015 | C3: =Financials!H8/Financials!H2 -> 0.3953793 | D3: =Financials!I8/Financials!I2 -> 0.45119306 | E3: =Financials!J8/Financials!J2 -> 0.38101748 | F3: =Financials!K8/Financials!K2 -> 0.16385911 | H3: =AVERAGE(B3:F3) -> 0.29866982 | I3: =MEDIAN(B3:F3) -> 0.38101748
A4: CapEx | B4: 5870000000 | C4: 6330000000 | D4: 9580000000 | E4: 12110000000 | F4: 14640000000
A5: D&A | B5: 11445000000 | C5: 11695000000 | D5: 13218000000 | E5: 13280000000 | F5: 12479000000
A6: Net Investment/Sales | B6: =(B4-B5)/Financials!G2 -> -0.10385618 | C6: =(C4-C5)/Financials!H2 -> -0.063891866 | D6: =(D4-D5)/Financials!I2 -> -0.029227926 | E6: =(E4-E5)/Financials!J2 -> -0.011424666 | F6: =(F4-F5)/Financials!K2 -> 0.023638154 | H6: =AVERAGE(B6:F6) -> -0.036952498 | I6: =MEDIAN(B6:F6) -> -0.029227926
A7: Account Receivables | B7: 7326000000 | C7: 7714000000 | D7: 6317000000 | E7: 7313000000 | F7: 5532000000
A8: Inventories | B8: 5677000000 | C8: 7255000000 | D8: 8779000000 | E8: 7681000000 | F8: 6710000000
A9: Account Payables | B9: 10551000000 | C9: 10217000000 | D9: 15566000000 | E9: 13818000000 | F9: 13423000000
A10: NWC/Sales | B10: =(B7+B8-B9)/Financials!G2 -> 0.045678092 | C10: =(C7+C8-C9)/Financials!H2 -> 0.05659164 | D10: =(D7+D8-D9)/Financials!I2 -> -0.0037760103 | E10: =(E7+E8-E9)/Financials!J2 -> 0.011483254 | F10: =(F7+F8-F9)/Financials!K2 -> -0.012918399 | H10: =AVERAGE(B10:F10) -> 0.019411715 | I10: =MEDIAN(B10:F10) -> 0.011483254
A11: Effective Tax Rate | B11: 0.31 | C11: 0.29 | D11: 0.31 | E11: 0.29 | F11: 0.32 | H11: =AVERAGE(B11:F11) -> 0.304 | I11: =MEDIAN(B11:F11) -> 0.31
A13: Revenue Growth (historical) | B13: -0.2991 | C13: 0.5641 | D13: 0.4824 | E13: -0.1773 | F13: -0.1073 | H13: =AVERAGE(B13:F13) -> 0.09256 | I13: =MEDIAN(B13:F13) -> -0.1073
A14: Long-run Growth | B14: 0.025
A15: rWACC | B15: ='Cost of Capital'!B28 -> 0.14249246
A16: rWACC w/out Cash | B16: ='Cost of Capital'!B29 -> 0.14536425
A18: Values in Dollar Billion
A19: t | B19: 0 | C19: 1 | D19: 2 | E19: 3 | F19: 4 | G19: 5 | H19: 6
A20: Sales | B20: =Financials!K2 -> 91420000000 | C20: =B20*(1+$H$13) -> 99881835200 | D20: =C20*(1+$H$13) -> 109126897866 | E20: =D20*(1+$H$13) -> 119227683533 | F20: =E20*(1+$H$13) -> 130263397920 | G20: =F20*(1+$H$13) -> 142320578032 | H20: =G20*(1+$H$13) -> 155493770735
A21: EBIT | C21: =C20*$H$3 -> 29831689746 | D21: =D20*$H$3 -> 32592910949 | E21: =E20*$H$3 -> 35609710786 | F21: =F20*$H$3 -> 38905745617 | G21: =G20*$H$3 -> 42506861431 | H21: =H20*$H$3 -> 46441296525
A22: NOPAT | C22: =C21*(1-$H$11) -> 20762856063 | D22: =D21*(1-$H$11) -> 22684666021 | E22: =E21*(1-$H$11) -> 24784358707 | F22: =F21*(1-$H$11) -> 27078398949 | G22: =G21*(1-$H$11) -> 29584775556 | H22: =H21*(1-$H$11) -> 32323142382
A23: Net Investment | C23: =(C20-B20)*$H$6 -> -3.1268595e+08 | D23: =(D20-C20)*$H$6 -> -3.4162816e+08 | E23: =(E20-D20)*$H$6 -> -3.7324926e+08 | F23: =(F20-E20)*$H$6 -> -4.0779721e+08 | G23: =(G20-F20)*$H$6 -> -4.4554292e+08 | H23: =(H20-G20)*$H$6 -> -4.8678238e+08
A24: Change NWC | C24: =(C20-B20)*$H$10 -> 1.6425874e+08 | D24: =(D20-C20)*$H$10 -> 1.7946253e+08 | E24: =(E20-D20)*$H$10 -> 1.9607358e+08 | F24: =(F20-E20)*$H$10 -> 2.1422215e+08 | G24: =(G20-F20)*$H$10 -> 2.3405055e+08 | H24: =(H20-G20)*$H$10 -> 2.5571427e+08
A25: FCF | C25: =C22-C23-C24 -> 20911283274 | D25: =D22-D23-D24 -> 22846831654 | E25: =E22-E23-E24 -> 24961534392 | F25: =F22-F23-F24 -> 27271974015 | G25: =G22-G23-G24 -> 29796267930 | H25: =H22-H23-H24 -> 32554210489
A27: Scenario I | I27: Scenario II | J27: Using rWACC w/out Cash
A28: PV GP5 | B28: =H25/(B15-B14) -> 277074888443 | I28: PV GP5 | J28: =H25/(B16-B14) -> 270464108273
A29: PV FCF 1-5 | B29: {=NPV(B15,C25:G25)} -> 83858714098 | I29: PV FCF 1-5 | J29: {=NPV(B16, C25:H25)} -> 97668038263
A30: Estimated EV | B30: =B29+B28/(1+B15)^5 -> 226199858279 | I30: Estimated EV | J30: =J29+J28/(1+B16)^5 -> 234879855657
A31: Total Debt | B31: =Financials!K22 -> 59350000000 | I31: Total Debt | J31: =Financials!K22 -> 59350000000
A32: Cash & Cash Equivalent | B32: =Financials!K23 -> 3270000000 | I32: Cash & Cash Equivalent | J32: =Financials!K23 -> 3270000000
A33: Shares Outstanding | B33: =Financials!K25 -> 6454643831 | I33: Shares Outstanding | J33: =Financials!K25 -> 6454643831
A34: Estimated Price | B34: =(B30-B31+B32)/B33 -> 26.356196 | I34: Estimated Price | J34: =(J30-J31+J32)/J33 -> 27.700964
A35: Share Price (1/2/25) | B35: 13.16 | I35: Share Price (1/2/25) | J35: 13.16

Sheet Cost of Capital
A1: Cost of Equity
A2: Risk-free Rate (rF) | B2: 0.1381
A3: Beta | B3: 0.86
A4: Alpha | B4: 0
A5: Risk Premium | B5: 0.0324
A6: Cost of Equity (rE) | B6: =B2+B3*B5 -> 0.165964
A8: Cost of Debt
A9: Interest Coverage | B9: ='Financial ratios'!M17 -> 4.7
A10: Synthetic Rating | B10: A2/A
A11: Spread | B11: 0.0078
A12: Risk-free Rate (rF) | B12: 0.1381
A13: Pre-tax Cost of Debt (rD) | B13: =B12+B11 -> 0.1459
A14: Effective Tax Rate | B14: =AVERAGE(DFCF!B11:F11) -> 0.304
A15: After-tax Cost of Debt | B15: =B13*(1-B14) -> 0.1015464
A17: Cost of Capital
A18: Shares Outstanding | B18: =Financials!K25 -> 6454643831
A19: Share Price | B19: 16.3
A20: Market Cap | B20: =B18*B19 -> 105210694445
A21: Total Debt | B21: =Financials!K21 -> 60310000000
A22: Cash & Cash Equivalent | B22: =Financials!K23 -> 3270000000
A23: Enterprise Value | B23: =B20+B21-B22 -> 162250694445
A24: Equity Weight (wE) | B24: =B20/(B20+B21) -> 0.63563468
A25: Debt Weight (wD) | B25: =B21/(B20+B21) -> 0.36436532
A27: rU | B27: =B24*B6+(B13*B25) -> 0.15865337
A28: rWACC | B28: =B24*B6+(B25*B15) -> 0.14249246
A29: rWACC w/out Cash | B29: =(B20/B23)*B6+(B21/B23)*B15 -> 0.14536425
